ttkbootstrap_icons_fa/__init__.py
ttkbootstrap_icons_fa/glyphmap-brands.json
ttkbootstrap_icons_fa/glyphmap-regular.json
ttkbootstrap_icons_fa/glyphmap-solid.json
ttkbootstrap_icons_fa/icon.py
ttkbootstrap_icons_fa/provider.py
ttkbootstrap_icons_fa/LICENSES/CC-BY-4.0.txt
ttkbootstrap_icons_fa/LICENSES/MIT.txt
ttkbootstrap_icons_fa/LICENSES/OFL-1.1.txt
ttkbootstrap_icons_fa/fonts/fa-brands-400.ttf
ttkbootstrap_icons_fa/fonts/fa-regular-400.ttf
ttkbootstrap_icons_fa/fonts/fa-solid-900.ttf
ttkbootstrap_icons_fa/tools/__init__.py
ttkbootstrap_icons_fa/tools/generate_assets.py
ttkbootstrap_icons_fa-1.0.2.dist-info/METADATA
ttkbootstrap_icons_fa-1.0.2.dist-info/WHEEL
ttkbootstrap_icons_fa-1.0.2.dist-info/entry_points.txt
ttkbootstrap_icons_fa-1.0.2.dist-info/top_level.txt
ttkbootstrap_icons_fa-1.0.2.dist-info/RECORD
